{
  "timestamp": 1755691393142,
  "alert_type": "correlation_breakdown",
  "alert_id": "corr_breakdown_eth-xrp_20250820_200313_142_acf86d34",
  "pair": "ETH_XRP",
  "pair_type": "crypto_crypto",
  "breakdown_details": {
    "current_correlation": 0.4326292506242935,
    "historical_average_correlation": 0.46475786658537066,
    "z_score": -2.8395650451630696,
    "significance_level": 0.0,
    "threshold_exceeded": true,
    "breakdown_direction": "negative",
    "severity": "high",
    "duration_minutes": 0
  },
  "market_context": {
    "asset1_price": 0.0,
    "asset1_24h_change": 0.0,
    "asset2_price": 0.0,
    "asset2_24h_change": 0.0,
    "market_volatility": "normal"
  },
  "statistical_analysis": {
    "correlation_windows": {
      "7d": 0.4326292506242935
    },
    "confidence_interval": {
      "lower": 0.4191759733114911,
      "upper": 0.44589258380022695
    },
    "p_value": 0.0,
    "sample_size": 100
  },
  "recommended_actions": [
    "Strong negative correlation breakdown detected",
    "Consider hedging strategies immediately",
    "High severity correlation change - monitor closely",
    "Watch for correlation normalization",
    "Consider position adjustments",
    "Monitor related asset pairs"
  ],
  "alert_metadata": {
    "severity": "high",
    "category": "correlation_analysis",
    "expires_at": 1755694993142,
    "related_pairs": []
  }
}