{
  "timestamp": 1756773445187,
  "asset": "ethereum",
  "signal_type": "SHORT",
  "direction": "SELL",
  "price": 4305.484167790153,
  "confidence": 1.0,
  "signal_strength": "STRONG",
  "strategy_name": "Aggregated_Signal",
  "position_size": 0.02,
  "stop_loss": 4520.758376179661,
  "take_profit": 3874.935751011138,
  "alert_type": "trading_signal",
  "analysis_data": {
    "aggregation_method": "weighted_average",
    "strategies_combined": [
      "vixcorrelation"
    ],
    "strategy_weights": {
      "vixcorrelation": 0.25
    },
    "signal_conflict_analysis": {
      "signal_count": 1,
      "unique_types": [
        